flake8_nested_fstrings.py
flake8_nested_fstrings-1.1.0.dist-info/LICENSE
flake8_nested_fstrings-1.1.0.dist-info/METADATA
flake8_nested_fstrings-1.1.0.dist-info/WHEEL
flake8_nested_fstrings-1.1.0.dist-info/entry_points.txt
flake8_nested_fstrings-1.1.0.dist-info/top_level.txt
flake8_nested_fstrings-1.1.0.dist-info/RECORD
