Metadata-Version: 2.1
Name: flake8-nested-fstrings
Version: 1.1.0
Summary: flake8 plugin which forbids nesting f-strings inside other f-strings.
Author-email: Ferran Jovell <ferran.jovell+gh@gmail.com>
License: MIT License
Keywords: flake8
Classifier: License :: OSI Approved :: MIT License
Classifier: Programming Language :: Python :: 3
Classifier: Programming Language :: Python :: 3 :: Only
Classifier: Programming Language :: Python :: 3.12
Classifier: Programming Language :: Python :: Implementation :: CPython
Requires-Python: >=3.12
License-File: LICENSE
Requires-Dist: flake8
Provides-Extra: test
Requires-Dist: pytest ; extra == 'test'
Requires-Dist: mypy ; extra == 'test'
